wikiglot/__init__.py
wikiglot/utils.py
wikiglot/wiktionary.py
wikiglot/data/da_lang_abbr.json
wikiglot/data/en_form_of.txt
wikiglot/data/en_lang_abbr.json
wikiglot/data/sv_lang_abbr.json
wikiglot/locale/__init__.py
wikiglot/locale/locale.py
wikiglot/locale/da/__init__.py
wikiglot/locale/en/__init__.py
wikiglot/locale/sv/__init__.py
wikiglot-0.2.1.dist-info/METADATA
wikiglot-0.2.1.dist-info/WHEEL
wikiglot-0.2.1.dist-info/licenses/LICENSE
wikiglot-0.2.1.dist-info/RECORD
