Metadata-Version: 2.3
Name: wikiglot
Version: 0.2.1
Summary: Yet another wiktionary parser
Project-URL: homepage, https://github.com/jolars/wikiglot
Project-URL: documentation, https://jolars.github.io/wikiglot/
Project-URL: changelog, https://github.com/jolars/wikiglot/blob/main/CHANGELOG.md
Project-URL: tracker, https://github.com/jolars/wikiglot/issues
Author-email: Johan Larsson <johanlarsson@outlook.com>
Maintainer-email: Johan Larsson <johanlarsson@outlook.com>
License: MIT License
License-File: LICENSE
Classifier: Development Status :: 3 - Alpha
Classifier: License :: OSI Approved :: MIT License
Classifier: Operating System :: MacOS
Classifier: Operating System :: Microsoft :: Windows
Classifier: Operating System :: POSIX
Classifier: Operating System :: POSIX :: Linux
Classifier: Operating System :: Unix
Classifier: Programming Language :: Python :: 3 :: Only
Classifier: Programming Language :: Python :: 3.10
Classifier: Programming Language :: Python :: 3.11
Classifier: Programming Language :: Python :: 3.12
Classifier: Topic :: Scientific/Engineering
Requires-Python: >=3.10
Requires-Dist: bs4
Requires-Dist: requests
Provides-Extra: docs
Requires-Dist: furo; extra == 'docs'
Requires-Dist: myst-parser; extra == 'docs'
Requires-Dist: sphinx; extra == 'docs'
Requires-Dist: sphinx-copybutton; extra == 'docs'
Provides-Extra: tests
Requires-Dist: pytest; extra == 'tests'
Requires-Dist: sphinx; extra == 'tests'
